bwnet/__init__.py
bwnet/client.py
bwnet/rcp.py
bwnet/server.py
bwnet/utils.py
bwnet-0.2.2.1.dist-info/LICENSE
bwnet-0.2.2.1.dist-info/METADATA
bwnet-0.2.2.1.dist-info/WHEEL
bwnet-0.2.2.1.dist-info/top_level.txt
bwnet-0.2.2.1.dist-info/RECORD
